nonebot_plugin_itnews/__init__.py
nonebot_plugin_itnews/itnews.py
nonebot_plugin_itnew-0.1.3.dist-info/LICENSE
nonebot_plugin_itnew-0.1.3.dist-info/METADATA
nonebot_plugin_itnew-0.1.3.dist-info/WHEEL
nonebot_plugin_itnew-0.1.3.dist-info/top_level.txt
nonebot_plugin_itnew-0.1.3.dist-info/RECORD
